README.rst
setup.py
easy_extract/__init__.py
easy_extract/archive.py
easy_extract/archive_finder.py
easy_extract.egg-info/PKG-INFO
easy_extract.egg-info/SOURCES.txt
easy_extract.egg-info/dependency_links.txt
easy_extract.egg-info/entry_points.txt
easy_extract.egg-info/not-zip-safe
easy_extract.egg-info/top_level.txt
easy_extract/archives/__init__.py
easy_extract/archives/hj_split.py
easy_extract/archives/media.py
easy_extract/archives/rar.py
easy_extract/archives/renamed.py
easy_extract/archives/seven_zip.py
easy_extract/archives/xtm.py
easy_extract/scripts/__init__.py
easy_extract/scripts/extract.py
easy_extract/scripts/index.py