Metadata-Version: 1.1
Name: easy-extract
Version: 0.1.2
Summary: Easy extraction of archives collections
Home-page: https://github.com/Fantomas42/easy-extract
Author: Fantomas42
Author-email: fantomas42@gmail.com
License: GPL
Keywords: extract,rar,zip,xtm,hjsplit
Platform: any
Classifier: Development Status :: 4 - Beta
Classifier: Intended Audience :: System Administrators
Classifier: Operating System :: POSIX :: Linux
Classifier: Programming Language :: Python
Classifier: Topic :: Utilities
